mathlib_basic/__init__.py
mathlib_basic/operations.py
tests/__init__.py
tests/test_operations.py
mathlib_basic-0.2.dist-info/METADATA
mathlib_basic-0.2.dist-info/WHEEL
mathlib_basic-0.2.dist-info/top_level.txt
mathlib_basic-0.2.dist-info/RECORD
