Metadata-Version: 2.1
Name: mathlib_basic
Version: 0.2
Summary: A Python library for basic mathematical operations
Author: Umut Topalak
Author-email: umuttopalak@hotmail.com
Classifier: Programming Language :: Python :: 3
Classifier: License :: OSI Approved :: MIT License
